rcpputils/_dummy.cpython-310-x86_64-linux-gnu.so
ros_rcpputils-2.13.5.data/data/include/rcpputils/rcpputils/asserts.hpp
ros_rcpputils-2.13.5.data/data/include/rcpputils/rcpputils/compile_warnings.hpp
ros_rcpputils-2.13.5.data/data/include/rcpputils/rcpputils/endian.hpp
ros_rcpputils-2.13.5.data/data/include/rcpputils/rcpputils/env.hpp
ros_rcpputils-2.13.5.data/data/include/rcpputils/rcpputils/filesystem_helper.hpp
ros_rcpputils-2.13.5.data/data/include/rcpputils/rcpputils/find_and_replace.hpp
ros_rcpputils-2.13.5.data/data/include/rcpputils/rcpputils/find_library.hpp
ros_rcpputils-2.13.5.data/data/include/rcpputils/rcpputils/join.hpp
ros_rcpputils-2.13.5.data/data/include/rcpputils/rcpputils/pointer_traits.hpp
ros_rcpputils-2.13.5.data/data/include/rcpputils/rcpputils/process.hpp
ros_rcpputils-2.13.5.data/data/include/rcpputils/rcpputils/rolling_mean_accumulator.hpp
ros_rcpputils-2.13.5.data/data/include/rcpputils/rcpputils/scope_exit.hpp
ros_rcpputils-2.13.5.data/data/include/rcpputils/rcpputils/shared_library.hpp
ros_rcpputils-2.13.5.data/data/include/rcpputils/rcpputils/split.hpp
ros_rcpputils-2.13.5.data/data/include/rcpputils/rcpputils/thread_safety_annotations.hpp
ros_rcpputils-2.13.5.data/data/include/rcpputils/rcpputils/time.hpp
ros_rcpputils-2.13.5.data/data/include/rcpputils/rcpputils/unique_lock.hpp
ros_rcpputils-2.13.5.data/data/include/rcpputils/rcpputils/version.h
ros_rcpputils-2.13.5.data/data/include/rcpputils/rcpputils/visibility_control.hpp
ros_rcpputils-2.13.5.data/data/include/rcpputils/rcpputils/tl_expected/expected.hpp
ros_rcpputils-2.13.5.data/data/lib/librcpputils.so
ros_rcpputils-2.13.5.data/data/share/ament_index/resource_index/package_run_dependencies/rcpputils
ros_rcpputils-2.13.5.data/data/share/ament_index/resource_index/packages/rcpputils
ros_rcpputils-2.13.5.data/data/share/ament_index/resource_index/parent_prefix_path/rcpputils
ros_rcpputils-2.13.5.data/data/share/rcpputils/local_setup.bash
ros_rcpputils-2.13.5.dist-info/METADATA
ros_rcpputils-2.13.5.dist-info/WHEEL
ros_rcpputils-2.13.5.dist-info/top_level.txt
ros_rcpputils-2.13.5.dist-info/RECORD
ros_rcpputils-2.13.5.dist-info/licenses/LICENSE
