Metadata-Version: 2.4
Name: ros-rcpputils
Version: 2.13.5
Summary: rcpputils is a ROS 2 C++ utilities package providing macros, functions, and data structures for various common tasks.
License-File: LICENSE
Requires-Dist: ros-rcutils~=6.9.8
Dynamic: description
Dynamic: description-content-type
Dynamic: license-file
Dynamic: requires-dist
Dynamic: summary
